lfcnn/__init__.py
lfcnn/_version.py
lfcnn/callbacks/__init__.py
lfcnn/callbacks/cyclic_learning.py
lfcnn/callbacks/lr_finder.py
lfcnn/callbacks/lr_schedules.py
lfcnn/callbacks/sacred.py
lfcnn/generators/__init__.py
lfcnn/generators/abstracts.py
lfcnn/generators/generators.py
lfcnn/generators/reshapes.py
lfcnn/generators/utils.py
lfcnn/layers/__init__.py
lfcnn/layers/layers.py
lfcnn/layers/masks/__init__.py
lfcnn/layers/masks/abstracts.py
lfcnn/layers/masks/callbacks.py
lfcnn/layers/masks/neural_fractal.py
lfcnn/losses/__init__.py
lfcnn/losses/combined_losses.py
lfcnn/losses/losses.py
lfcnn/metrics/__init__.py
lfcnn/metrics/metrics.py
lfcnn/models/__init__.py
lfcnn/models/abstracts.py
lfcnn/models/autoencoder/__init__.py
lfcnn/models/autoencoder/conv3dmodel.py
lfcnn/models/autoencoder/dummy.py
lfcnn/models/autoencoder/epi_volume_encoder.py
lfcnn/models/center_and_disparity/__init__.py
lfcnn/models/center_and_disparity/conv3d_decode2d.py
lfcnn/models/center_and_disparity/conv3d_decode2d_st.py
lfcnn/models/center_and_disparity/conv4d_decode2d.py
lfcnn/models/center_and_disparity/dictionary_sparse_coding_epinet.py
lfcnn/models/center_and_disparity/dummy.py
lfcnn/models/disparity/__init__.py
lfcnn/models/disparity/conv2dmodel.py
lfcnn/models/disparity/conv3dmodel.py
lfcnn/models/disparity/dummy.py
lfcnn/models/disparity/epinet.py
lfcnn/models/disparity/lfattnet.py
lfcnn/models/disparity/vommanet.py
lfcnn/models/sparse_coding/__init__.py
lfcnn/models/sparse_coding/dictionary_sparse_coding.py
lfcnn/models/sparse_coding/utils/__init__.py
lfcnn/models/sparse_coding/utils/patching.py
lfcnn/models/sparse_coding/utils/sparse_coding.py
lfcnn/models/sparse_coding/utils/sparse_tensor_coding.py
lfcnn/models/superresolution/__init__.py
lfcnn/models/superresolution/dummy.py
lfcnn/models/superresolution/sas_conv.py
lfcnn/training/__init__.py
lfcnn/training/auxiliary_loss/__init__.py
lfcnn/training/auxiliary_loss/gradient_similarity.py
lfcnn-0.4.1.dist-info/AUTHORS
lfcnn-0.4.1.dist-info/LICENSE
lfcnn-0.4.1.dist-info/METADATA
lfcnn-0.4.1.dist-info/WHEEL
lfcnn-0.4.1.dist-info/top_level.txt
lfcnn-0.4.1.dist-info/zip-safe
lfcnn-0.4.1.dist-info/RECORD
