Metadata-Version: 2.1
Name: lfcnn
Version: 0.4.1
Summary: A TensorFlow framework for light field deep learning.
Home-page: https://gitlab.com/iiit-public/lfcnn
Author: Maximilian Schambach
Author-email: schambach@kit.edu
License: GNU General Public License v3 (GPLv3)
Platform: UNKNOWN
Classifier: Programming Language :: Python :: 3.6
Classifier: Programming Language :: Python :: 3.7
Classifier: Programming Language :: Python :: 3.8
Classifier: License :: OSI Approved :: GNU General Public License v3 (GPLv3)
Classifier: Operating System :: OS Independent
Classifier: Development Status :: 4 - Beta
Requires-Python: >=3.6
License-File: LICENSE
License-File: AUTHORS
Requires-Dist: tensorflow (>=2.2)
Requires-Dist: h5py (<3.0,>=2.10)
Requires-Dist: numpy (>=1.18)
Requires-Dist: scipy (>=1.4)
Requires-Dist: imageio (>=2.3.0)
Provides-Extra: sacred
Requires-Dist: sacred ; extra == 'sacred'
Requires-Dist: pymongo ; extra == 'sacred'
Provides-Extra: utils
Requires-Dist: plenpy ; extra == 'utils'
Requires-Dist: matplotlib ; extra == 'utils'
